kbbi_mcp/__init__.py
kbbi_mcp/__main__.py
kbbi_mcp/api.py
kbbi_mcp/py.typed
kbbi_mcp/server.py
kbbi_mcp/settings.py
kbbi_mcp/types.py
kbbi_mcp-0.0.3.dist-info/licenses/LICENSE
kbbi_mcp-0.0.3.dist-info/licenses/NOTICE
kbbi_mcp-0.0.3.dist-info/WHEEL
kbbi_mcp-0.0.3.dist-info/entry_points.txt
kbbi_mcp-0.0.3.dist-info/METADATA
kbbi_mcp-0.0.3.dist-info/RECORD
