Metadata-Version: 2.4
Name: kbbi-mcp
Version: 0.0.3
Summary: A simple MCP server for querying KBBI (Indonesian dictionary)
Keywords: mcp,kbbi,dictionary,indonesian,fastmcp
Author: Gakuto Furuya
Author-email: Gakuto Furuya <57865205+gaato@users.noreply.github.com>
License-Expression: Apache-2.0
License-File: LICENSE
License-File: NOTICE
Classifier: Development Status :: 3 - Alpha
Classifier: Intended Audience :: Developers
Classifier: Programming Language :: Python :: 3
Classifier: Programming Language :: Python :: 3 :: Only
Classifier: Programming Language :: Python :: 3.13
Classifier: Programming Language :: Python :: 3.14
Classifier: Programming Language :: Python :: Implementation :: CPython
Classifier: Typing :: Typed
Classifier: Topic :: Software Development :: Libraries
Requires-Dist: fastmcp>=2.14.1,<3
Requires-Dist: kbbi>=0.4.3
Requires-Dist: pydantic-settings>=2,<3
Requires-Dist: ruff>=0.14.10 ; extra == 'dev'
Requires-Dist: ty>=0.0.7 ; extra == 'dev'
Requires-Dist: pytest>=8,<9 ; extra == 'dev'
Requires-Python: >=3.13
Project-URL: Issues, https://github.com/gaato/kbbi-mcp/issues
Project-URL: Repository, https://github.com/gaato/kbbi-mcp
Provides-Extra: dev
